multi_agent_orchestrator/__init__.py
multi_agent_orchestrator/orchestrator.py
multi_agent_orchestrator/agents/__init__.py
multi_agent_orchestrator/agents/agent.py
multi_agent_orchestrator/agents/amazon_bedrock_agent.py
multi_agent_orchestrator/agents/anthropic_agent.py
multi_agent_orchestrator/agents/bedrock_flows_agent.py
multi_agent_orchestrator/agents/bedrock_inline_agent.py
multi_agent_orchestrator/agents/bedrock_llm_agent.py
multi_agent_orchestrator/agents/bedrock_translator_agent.py
multi_agent_orchestrator/agents/chain_agent.py
multi_agent_orchestrator/agents/comprehend_filter_agent.py
multi_agent_orchestrator/agents/lambda_agent.py
multi_agent_orchestrator/agents/lex_bot_agent.py
multi_agent_orchestrator/agents/openai_agent.py
multi_agent_orchestrator/agents/supervisor_agent.py
multi_agent_orchestrator/classifiers/__init__.py
multi_agent_orchestrator/classifiers/anthropic_classifier.py
multi_agent_orchestrator/classifiers/bedrock_classifier.py
multi_agent_orchestrator/classifiers/classifier.py
multi_agent_orchestrator/classifiers/openai_classifier.py
multi_agent_orchestrator/retrievers/__init__.py
multi_agent_orchestrator/retrievers/amazon_kb_retriever.py
multi_agent_orchestrator/retrievers/retriever.py
multi_agent_orchestrator/shared/__init__.py
multi_agent_orchestrator/shared/user_agent.py
multi_agent_orchestrator/shared/version.py
multi_agent_orchestrator/storage/__init__.py
multi_agent_orchestrator/storage/chat_storage.py
multi_agent_orchestrator/storage/dynamodb_chat_storage.py
multi_agent_orchestrator/storage/in_memory_chat_storage.py
multi_agent_orchestrator/storage/sql_chat_storage.py
multi_agent_orchestrator/types/__init__.py
multi_agent_orchestrator/types/types.py
multi_agent_orchestrator/utils/__init__.py
multi_agent_orchestrator/utils/helpers.py
multi_agent_orchestrator/utils/logger.py
multi_agent_orchestrator/utils/tool.py
multi_agent_orchestrator-0.1.15.dist-info/licenses/LICENSE
multi_agent_orchestrator-0.1.15.dist-info/METADATA
multi_agent_orchestrator-0.1.15.dist-info/WHEEL
multi_agent_orchestrator-0.1.15.dist-info/entry_points.txt
multi_agent_orchestrator-0.1.15.dist-info/top_level.txt
multi_agent_orchestrator-0.1.15.dist-info/RECORD
