Metadata-Version: 2.4
Name: multi_agent_orchestrator
Version: 0.1.15
Summary: DEPRECATED: Use 'agent-squad' instead. Multi-agent orchestrator framework.
Home-page: https://github.com/awslabs/multi-agent-orchestrator
Author: Anthony Bernabeu, Corneliu Croitoru
Author-email: brnaba@amazon.com, ccroito@amazon.com
License: Apache License 2.0
Classifier: Programming Language :: Python :: 3
Classifier: License :: OSI Approved :: Apache Software License
Classifier: Operating System :: OS Independent
Requires-Python: >=3.11
License-File: LICENSE
Provides-Extra: aws
Requires-Dist: boto3>=1.36.18; extra == "aws"
Provides-Extra: anthropic
Requires-Dist: anthropic>=0.40.0; extra == "anthropic"
Provides-Extra: openai
Requires-Dist: openai>=1.55.3; extra == "openai"
Provides-Extra: sql
Requires-Dist: libsql-client>=0.3.1; extra == "sql"
Provides-Extra: all
Requires-Dist: anthropic>=0.40.0; extra == "all"
Requires-Dist: openai>=1.55.3; extra == "all"
Requires-Dist: boto3>=1.36.18; extra == "all"
Requires-Dist: libsql-client>=0.3.1; extra == "all"
Dynamic: license-file
